pathogen/core.py
pathogen/version.py
pathogen-0.0.dev2.dist-info/LICENSE.md
pathogen-0.0.dev2.dist-info/METADATA
pathogen-0.0.dev2.dist-info/WHEEL
pathogen-0.0.dev2.dist-info/top_level.txt
pathogen-0.0.dev2.dist-info/RECORD
