Metadata-Version: 2.1
Name: pathogen
Version: 0.0.dev2
Summary: Helper functions for paths
Home-page: https://www.lockhartlab.org
Author: C. Lockhart
Author-email: chris@lockhartlab.org
License: UNKNOWN
Platform: UNKNOWN
